setup.py
wordnik/AccountApi.py
wordnik/WordApi.py
wordnik/WordListApi.py
wordnik/WordListsApi.py
wordnik/WordsApi.py
wordnik/__init__.py
wordnik/swagger.py
wordnik/models/ApiTokenStatus.py
wordnik/models/AudioFile.py
wordnik/models/AuthenticationToken.py
wordnik/models/Bigram.py
wordnik/models/Citation.py
wordnik/models/ContentProvider.py
wordnik/models/Definition.py
wordnik/models/DefinitionSearchResults.py
wordnik/models/Example.py
wordnik/models/ExampleSearchResults.py
wordnik/models/ExampleUsage.py
wordnik/models/Facet.py
wordnik/models/FacetValue.py
wordnik/models/Frequency.py
wordnik/models/FrequencySummary.py
wordnik/models/Label.py
wordnik/models/Note.py
wordnik/models/Related.py
wordnik/models/ScoredWord.py
wordnik/models/ScrabbleScoreResult.py
wordnik/models/Sentence.py
wordnik/models/SimpleDefinition.py
wordnik/models/SimpleExample.py
wordnik/models/StringValue.py
wordnik/models/Syllable.py
wordnik/models/TextPron.py
wordnik/models/User.py
wordnik/models/WordList.py
wordnik/models/WordListWord.py
wordnik/models/WordObject.py
wordnik/models/WordOfTheDay.py
wordnik/models/WordSearchResult.py
wordnik/models/WordSearchResults.py
wordnik/models/__init__.py
wordnik_py3.egg-info/PKG-INFO
wordnik_py3.egg-info/SOURCES.txt
wordnik_py3.egg-info/dependency_links.txt
wordnik_py3.egg-info/top_level.txt