Metadata-Version: 1.0
Name: wordnik-py3
Version: 2.1
Summary: Wordnik API for Python3
Home-page: http://developer.wordnik.com
Author: Russell Horton
Author-email: russ@wordnik.com
License: UNKNOWN
Platform: UNKNOWN
